{
  "version": 1,
  "projectName": "",
  "reviewer": "",
  "checks": {
    "infra-01": {
      "checked": false,
      "by": "Simon",
      "at": 1782756329149
    },
    "ci-05": {
      "checked": true,
      "by": "Simon",
      "at": 1782763482978
    },
    "pm-01": {
      "checked": true,
      "by": "Simon",
      "at": 1782763496311
    }
  },
  "roadmap": {
    "layout": {
      "project-mgmt": {
        "startDay": 0,
        "span": 3
      },
      "infra": {
        "startDay": 1,
        "span": 3
      },
      "governance": {
        "startDay": 2,
        "span": 3
      },
      "lookml": {
        "startDay": 5,
        "span": 5
      },
      "cicd": {
        "startDay": 8,
        "span": 3
      },
      "content": {
        "startDay": 10,
        "span": 2
      },
      "adoption": {
        "startDay": 1,
        "span": 12
      },
      "platform": {
        "startDay": 11,
        "span": 2
      }
    },
    "startDate": "2026-06-29",
    "updatedAt": 1782767457930
  },
  "weeklies": [
    {
      "id": "w-1782764950020-muyei",
      "date": "2026-06-29",
      "title": "Kickoff",
      "participants": "Simon, Chaima, Hamza, Alexandre",
      "notes": "Phase de cadrage rapide : le client a d脙聝脗聝脙聜脗漏j脙聝脗聝脙聜脗聽 identifi脙聝脗聝脙聜脗漏 ses besoins. L脙聝脗垄脙聜脗聙脙聜脗聶objectif serait脙聝脗聜脙聜脗聽 principalement de faire un r脙聝脗聝脙聜脗漏capitulatif des attentes et de r脙聝脗聝脙聜脗漏aliser un audit technique de notre c脙聝脗聝脙聜脗麓t脙聝脗聝脙聜脗漏.\nPoints de suivi op脙聝脗聝脙聜脗漏rationnel : mise en place de deux points hebdomadaires, sans la participation de C脙聝脗聝脙聜脗漏dric :\nmercredi 脙聝脗聝脙聜脗聽 15h \nvendredi 脙聝脗聝脙聜脗聽 14h.\n\npoint mensuel avec Hamza, Alexandre et C脙聝脗聝脙聜脗漏dric : r脙聝脗聝脙聜脗漏utilisation d脙聝脗垄脙聜脗聙脙聜脗聶un des cr脙聝脗聝脙聜脗漏neaux actuellement utilis脙聝脗聝脙聜脗漏s pour les points hebdomadaires.\nPoint avec les 脙聝脗聝脙聜脗漏quipes m脙聝脗聝脙聜脗漏tier afin de valider l脙聝脗垄脙聜脗聙脙聜脗聶脙聝脗聝脙聜脗漏tape d脙聝脗垄脙聜脗聙脙聜脗聶脙聝脗聝脙聜脗漏vang脙聝脗聝脙聜脗漏lisation et les dashboards (politique)\nRLS  : 脙聝脗聝脙聜脗聽 pr脙聝脗聝脙聜脗漏voir d脙聝脗聝脙聜脗篓s le d脙聝脗聝脙聜脗漏marrage du projet. Il n脙聝脗垄脙聜脗聙脙聜脗聶existe actuellement pas de documentation sur ce point.\nAspect IA : 脙聝脗聝脙聜脗聽 discuter afin de d脙聝脗聝脙聜脗漏terminer si ce sujet fera partie du p脙聝脗聝脙聜脗漏rim脙聝脗聝脙聜脗篓tre du projet.",
      "actions": "",
      "updatedAt": 1782764950020,
      "createdAt": 1782764950020
    },
    {
      "id": "w-1782768872663-d0u5n",
      "date": "2026-06-29",
      "title": "Kickoff",
      "participants": "",
      "notes": "Phase de cadrage rapide : le client a d茅j脿 identifi茅 ses besoins. L鈥檕bjectif serait聽 principalement de faire un r茅capitulatif des attentes et de r茅aliser un audit technique de notre c么t茅.\nPoints de suivi op茅rationnel : mise en place de deux points hebdomadaires, sans la participation de C茅dric :\nmercredi 脿 15h \nvendredi 脿 14h.\n\npoint mensuel avec Hamza, Alexandre et C茅dric : r茅utilisation d鈥檜n des cr茅neaux actuellement utilis茅s pour les points hebdomadaires.\nPoint avec les 茅quipes m茅tier afin de valider l鈥櫭﹖ape d鈥櫭﹙ang茅lisation et les dashboards (politique)\nRLS  : 脿 pr茅voir d猫s le d茅marrage du projet. Il n鈥檈xiste actuellement pas de documentation sur ce point.\nAspect IA : 脿 discuter afin de d茅terminer si ce sujet fera partie du p茅rim猫tre du projet.",
      "actions": "",
      "updatedAt": 1782768872663,
      "createdAt": 1782768872663
    }
  ],
  "todos": [],
  "openPhases": [
    "infra",
    "lookml"
  ],
  "updatedAt": 1782768873300
}